pyising-0.1.2.data/data/CMakeLists.txt
pyising-0.1.2.data/data/src/bindings.cpp
pyising-0.1.2.data/data/src/parallel_progressbar.cpp
pyising-0.1.2.data/data/src/main.cpp
pyising-0.1.2.data/data/src/ising.hpp
pyising-0.1.2.data/data/src/ising.cpp
pyising-0.1.2.data/data/cnpy/npz2mat
pyising-0.1.2.data/data/cnpy/LICENSE
pyising-0.1.2.data/data/cnpy/cnpy.h
pyising-0.1.2.data/data/cnpy/cnpy.cpp
pyising-0.1.2.data/data/cnpy/npy2mat
pyising-0.1.2.data/data/cnpy/CMakeLists.txt
pyising-0.1.2.data/data/cnpy/example1.cpp
pyising-0.1.2.data/data/cnpy/mat2npz
pyising-0.1.2.data/data/cnpy/README.md
pyising-0.1.2.dist-info/WHEEL
pyising-0.1.2.dist-info/RECORD
pyising-0.1.2.dist-info/top_level.txt
pyising-0.1.2.dist-info/METADATA
pyising/_pyising.cpython-310-x86_64-linux-gnu.so
pyising/libcnpy.so
pyising/__init__.py
pyising/lib/libcnpy.a
pyising/lib/libcnpy.so
pyising/lib/libising.a
pyising/bin/npz2mat
pyising/bin/npy2mat
pyising/bin/mat2npz
pyising/include/cnpy.h
pyising.libs/libgcc_s-a0b57c20.so.1
pyising.libs/libstdc++-0d31ccbe.so.6.0.32
pyising.libs/libgomp-ba615989.so.1.0.0
